setup.py
grafeat_core_constants/__init__.py
grafeat_core_constants/node_float.py
grafeat_core_constants/node_int.py
grafeat_core_constants.egg-info/PKG-INFO
grafeat_core_constants.egg-info/SOURCES.txt
grafeat_core_constants.egg-info/dependency_links.txt
grafeat_core_constants.egg-info/top_level.txt