Metadata-Version: 1.0
Name: grafeat-core-constants
Version: 0.0.1
Summary: Core plugins for grafeat.
Home-page: https://github.com/syntheticastudio/grafeat_plugins
Author: Ruben Henares
Author-email: ruben@syntheticastudio.com
License: UNKNOWN
Keywords: grafeat,plugins
Platform: UNKNOWN
